<?xml version='1.0' encoding='UTF-8'?>
<DEFECTS><DEFECT><SFA><FILEPATH>c:\users\marcus\documents\github\x2d-game-engine\lib\vld-2.2.3\src\</FILEPATH><FILENAME>criticalsection.h</FILENAME><LINE>12</LINE><COLUMN>78</COLUMN></SFA><DEFECTCODE>28125</DEFECTCODE><DESCRIPTION>The function 'InitializeCriticalSection' must be called from within a try/except block:  The requirement might be conditional.</DESCRIPTION><FUNCTION>CriticalSection::Initialize</FUNCTION><DECORATED>?Initialize@CriticalSection@@QAEXXZ</DECORATED><FUNCLINE>12</FUNCLINE><PATH/></DEFECT><DEFECT><SFA><FILEPATH>c:\users\marcus\documents\github\x2d-game-engine\lib\vld-2.2.3\src\</FILEPATH><FILENAME>ntapi.h</FILENAME><LINE>35</LINE><COLUMN>13</COLUMN></SFA><DEFECTCODE>28251</DEFECTCODE><DESCRIPTION>Inconsistent annotation for 'NTSTATUS': this instance has no annotations. See c:\program files (x86)\windows kits\8.1\include\shared\bcrypt.h(29). Note: There are several prototypes for this function. This warning compares the first with instance number 3. </DESCRIPTION><FUNCTION></FUNCTION><DECORATED></DECORATED><FUNCLINE>0</FUNCLINE><PATH/></DEFECT><DEFECT><SFA><FILEPATH>c:\users\marcus\documents\github\x2d-game-engine\lib\vld-2.2.3\src\</FILEPATH><FILENAME>vld_hooks.cpp</FILENAME><LINE>1736</LINE><COLUMN>18</COLUMN></SFA><DEFECTCODE>6001</DEFECTCODE><DESCRIPTION>Using uninitialized memory 'mem'.</DESCRIPTION><FUNCTION>VisualLeakDetector::_HeapReAlloc</FUNCTION><DECORATED>?_HeapReAlloc@VisualLeakDetector@@CGPAXPAXK0K@Z</DECORATED><FUNCLINE>1705</FUNCLINE><PROBABILITY>1</PROBABILITY><RANK>3</RANK><CATEGORY><RULECATEGORY>mspft</RULECATEGORY></CATEGORY><PATH><SFA><FILEPATH>c:\users\marcus\documents\github\x2d-game-engine\lib\vld-2.2.3\src\</FILEPATH><FILENAME>vld_hooks.cpp</FILENAME><LINE>1707</LINE><COLUMN>25</COLUMN></SFA><SFA><FILEPATH>c:\users\marcus\documents\github\x2d-game-engine\lib\vld-2.2.3\src\</FILEPATH><FILENAME>vld_hooks.cpp</FILENAME><LINE>1710</LINE><COLUMN>11</COLUMN><KEYEVENT><ID>1</ID><KIND>declaration</KIND><IMPORTANCE>Essential</IMPORTANCE><MESSAGE>'mem' is not initialized</MESSAGE></KEYEVENT></SFA><SFA><FILEPATH>c:\users\marcus\documents\github\x2d-game-engine\lib\vld-2.2.3\src\</FILEPATH><FILENAME>vld_hooks.cpp</FILENAME><LINE>1711</LINE><COLUMN>15</COLUMN><KEYEVENT><ID>2</ID><KIND>branch</KIND><IMPORTANCE>Full</IMPORTANCE><MESSAGE>Skip this branch, (assume 'newmem==0' is false)</MESSAGE></KEYEVENT></SFA><SFA><FILEPATH>c:\users\marcus\documents\github\x2d-game-engine\lib\vld-2.2.3\src\</FILEPATH><FILENAME>vld_hooks.cpp</FILENAME><LINE>1714</LINE><COLUMN>11</COLUMN></SFA><SFA><FILEPATH>c:\users\marcus\documents\github\x2d-game-engine\lib\vld-2.2.3\src\</FILEPATH><FILENAME>vld_hooks.cpp</FILENAME><LINE>1715</LINE><COLUMN>24</COLUMN></SFA><SFA><FILEPATH>c:\users\marcus\documents\github\x2d-game-engine\lib\vld-2.2.3\src\</FILEPATH><FILENAME>vld_hooks.cpp</FILENAME><LINE>1716</LINE><COLUMN>9</COLUMN></SFA><SFA><FILEPATH>c:\users\marcus\documents\github\x2d-game-engine\lib\vld-2.2.3\src\</FILEPATH><FILENAME>vld_hooks.cpp</FILENAME><LINE>1717</LINE><COLUMN>14</COLUMN></SFA><SFA><FILEPATH>c:\users\marcus\documents\github\x2d-game-engine\lib\vld-2.2.3\src\</FILEPATH><FILENAME>vld_hooks.cpp</FILENAME><LINE>1718</LINE><COLUMN>8</COLUMN></SFA><SFA><FILEPATH>c:\users\marcus\documents\github\x2d-game-engine\lib\vld-2.2.3\src\</FILEPATH><FILENAME>vld_hooks.cpp</FILENAME><LINE>1724</LINE><COLUMN>16</COLUMN></SFA><SFA><FILEPATH>c:\users\marcus\documents\github\x2d-game-engine\lib\vld-2.2.3\src\</FILEPATH><FILENAME>vld_hooks.cpp</FILENAME><LINE>1726</LINE><COLUMN>24</COLUMN><KEYEVENT><ID>3</ID><KIND>branch</KIND><IMPORTANCE>Full</IMPORTANCE><MESSAGE>Skip this branch, (assume '&lt;branch condition&gt;' is false)</MESSAGE></KEYEVENT></SFA><SFA><FILEPATH>c:\users\marcus\documents\github\x2d-game-engine\lib\vld-2.2.3\src\</FILEPATH><FILENAME>vld_hooks.cpp</FILENAME><LINE>1729</LINE><COLUMN>19</COLUMN></SFA><SFA><FILEPATH>c:\users\marcus\documents\github\x2d-game-engine\lib\vld-2.2.3\src\</FILEPATH><FILENAME>vld_hooks.cpp</FILENAME><LINE>1736</LINE><COLUMN>18</COLUMN><KEYEVENT><ID>4</ID><KIND>declaration</KIND><IMPORTANCE>Full</IMPORTANCE><MESSAGE>'mem' is an In/Out argument to 'VisualLeakDetector::ReAllocateHeap' (declared at c:\users\marcus\documents\github\x2d-game-engine\lib\vld-2.2.3\src\vldint.h:338)</MESSAGE></KEYEVENT></SFA><SFA><FILEPATH>c:\users\marcus\documents\github\x2d-game-engine\lib\vld-2.2.3\src\</FILEPATH><FILENAME>vld_hooks.cpp</FILENAME><LINE>1736</LINE><COLUMN>18</COLUMN><KEYEVENT><ID>5</ID><KIND>usage</KIND><IMPORTANCE>Essential</IMPORTANCE><MESSAGE>'mem' is used, but may not have been initialized</MESSAGE></KEYEVENT></SFA></PATH></DEFECT><DEFECT><SFA><FILEPATH>c:\users\marcus\documents\github\x2d-game-engine\lib\vld-2.2.3\src\</FILEPATH><FILENAME>vldint.h</FILENAME><LINE>244</LINE><COLUMN>22</COLUMN></SFA><DEFECTCODE>28204</DEFECTCODE><DESCRIPTION>'DidAlloc' : Only one of this override and the one at c:\program files (x86)\windows kits\8.1\include\um\objidlbase.h(1165) are annotated for _Param_(1): both or neither must be annotated.</DESCRIPTION><FUNCTION></FUNCTION><DECORATED></DECORATED><FUNCLINE>0</FUNCLINE><PATH/></DEFECT><DEFECT><SFA><FILEPATH>c:\users\marcus\documents\github\x2d-game-engine\lib\vld-2.2.3\src\</FILEPATH><FILENAME>vld_hooks.cpp</FILENAME><LINE>1983</LINE><COLUMN>33</COLUMN></SFA><DEFECTCODE>28204</DEFECTCODE><DESCRIPTION>[Warning applies to VisualLeakDetector::DidAlloc at c:\users\marcus\documents\github\x2d-game-engine\lib\vld-2.2.3\src\vldint.h(244)]'DidAlloc' : Only one of this override and the one at c:\program files (x86)\windows kits\8.1\include\um\objidlbase.h(1165) are annotated for _Param_(1): both or neither must be annotated.</DESCRIPTION><FUNCTION></FUNCTION><DECORATED></DECORATED><FUNCLINE>0</FUNCLINE><PATH/></DEFECT><DEFECT><SFA><FILEPATH>c:\users\marcus\documents\github\x2d-game-engine\lib\vld-2.2.3\src\</FILEPATH><FILENAME>vldint.h</FILENAME><LINE>245</LINE><COLUMN>22</COLUMN></SFA><DEFECTCODE>28204</DEFECTCODE><DESCRIPTION>'Free' : Only one of this override and the one at c:\program files (x86)\windows kits\8.1\include\um\objidlbase.h(1157) are annotated for _Param_(1): both or neither must be annotated.</DESCRIPTION><FUNCTION></FUNCTION><DECORATED></DECORATED><FUNCLINE>0</FUNCLINE><PATH/></DEFECT><DEFECT><SFA><FILEPATH>c:\users\marcus\documents\github\x2d-game-engine\lib\vld-2.2.3\src\</FILEPATH><FILENAME>vld_hooks.cpp</FILENAME><LINE>1998</LINE><COLUMN>30</COLUMN></SFA><DEFECTCODE>28204</DEFECTCODE><DESCRIPTION>[Warning applies to VisualLeakDetector::Free at c:\users\marcus\documents\github\x2d-game-engine\lib\vld-2.2.3\src\vldint.h(245)]'Free' : Only one of this override and the one at c:\program files (x86)\windows kits\8.1\include\um\objidlbase.h(1157) are annotated for _Param_(1): both or neither must be annotated.</DESCRIPTION><FUNCTION></FUNCTION><DECORATED></DECORATED><FUNCLINE>0</FUNCLINE><PATH/></DEFECT><DEFECT><SFA><FILEPATH>c:\users\marcus\documents\github\x2d-game-engine\lib\vld-2.2.3\src\</FILEPATH><FILENAME>vldint.h</FILENAME><LINE>246</LINE><COLUMN>22</COLUMN></SFA><DEFECTCODE>28204</DEFECTCODE><DESCRIPTION>'GetSize' : Only one of this override and the one at c:\program files (x86)\windows kits\8.1\include\um\objidlbase.h(1161) are annotated for _Param_(1): both or neither must be annotated.</DESCRIPTION><FUNCTION></FUNCTION><DECORATED></DECORATED><FUNCLINE>0</FUNCLINE><PATH/></DEFECT><DEFECT><SFA><FILEPATH>c:\users\marcus\documents\github\x2d-game-engine\lib\vld-2.2.3\src\</FILEPATH><FILENAME>vld_hooks.cpp</FILENAME><LINE>2014</LINE><COLUMN>35</COLUMN></SFA><DEFECTCODE>28204</DEFECTCODE><DESCRIPTION>[Warning applies to VisualLeakDetector::GetSize at c:\users\marcus\documents\github\x2d-game-engine\lib\vld-2.2.3\src\vldint.h(246)]'GetSize' : Only one of this override and the one at c:\program files (x86)\windows kits\8.1\include\um\objidlbase.h(1161) are annotated for _Param_(1): both or neither must be annotated.</DESCRIPTION><FUNCTION></FUNCTION><DECORATED></DECORATED><FUNCLINE>0</FUNCLINE><PATH/></DEFECT><DEFECT><SFA><FILEPATH>c:\users\marcus\documents\github\x2d-game-engine\lib\vld-2.2.3\src\</FILEPATH><FILENAME>vldint.h</FILENAME><LINE>249</LINE><COLUMN>22</COLUMN></SFA><DEFECTCODE>28204</DEFECTCODE><DESCRIPTION>'Realloc' : Only one of this override and the one at c:\program files (x86)\windows kits\8.1\include\um\objidlbase.h(1151) are annotated for _Param_(1): both or neither must be annotated.</DESCRIPTION><FUNCTION></FUNCTION><DECORATED></DECORATED><FUNCLINE>0</FUNCLINE><PATH/></DEFECT><DEFECT><SFA><FILEPATH>c:\users\marcus\documents\github\x2d-game-engine\lib\vld-2.2.3\src\</FILEPATH><FILENAME>vld_hooks.cpp</FILENAME><LINE>2067</LINE><COLUMN>35</COLUMN></SFA><DEFECTCODE>28204</DEFECTCODE><DESCRIPTION>[Warning applies to VisualLeakDetector::Realloc at c:\users\marcus\documents\github\x2d-game-engine\lib\vld-2.2.3\src\vldint.h(249)]'Realloc' : Only one of this override and the one at c:\program files (x86)\windows kits\8.1\include\um\objidlbase.h(1151) are annotated for _Param_(1): both or neither must be annotated.</DESCRIPTION><FUNCTION></FUNCTION><DECORATED></DECORATED><FUNCLINE>0</FUNCLINE><PATH/></DEFECT></DEFECTS>